odoo/addons/sale_stock_cancel_restriction/README.rst
odoo/addons/sale_stock_cancel_restriction/__init__.py
odoo/addons/sale_stock_cancel_restriction/__manifest__.py
odoo/addons/sale_stock_cancel_restriction/i18n/es.po
odoo/addons/sale_stock_cancel_restriction/i18n/it.po
odoo/addons/sale_stock_cancel_restriction/i18n/pt.po
odoo/addons/sale_stock_cancel_restriction/i18n/sale_stock_cancel_restriction.pot
odoo/addons/sale_stock_cancel_restriction/models/__init__.py
odoo/addons/sale_stock_cancel_restriction/models/sale_order.py
odoo/addons/sale_stock_cancel_restriction/readme/CONTRIBUTORS.md
odoo/addons/sale_stock_cancel_restriction/readme/DESCRIPTION.md
odoo/addons/sale_stock_cancel_restriction/readme/USAGE.md
odoo/addons/sale_stock_cancel_restriction/static/description/icon.png
odoo/addons/sale_stock_cancel_restriction/static/description/index.html
odoo/addons/sale_stock_cancel_restriction/tests/__init__.py
odoo/addons/sale_stock_cancel_restriction/tests/test_sale_stock_cancel_restriction.py
odoo_addon_sale_stock_cancel_restriction-18.0.1.0.0.3.dist-info/METADATA
odoo_addon_sale_stock_cancel_restriction-18.0.1.0.0.3.dist-info/WHEEL
odoo_addon_sale_stock_cancel_restriction-18.0.1.0.0.3.dist-info/top_level.txt
odoo_addon_sale_stock_cancel_restriction-18.0.1.0.0.3.dist-info/RECORD
